Misalignmentpgm/__init__.py
Misalignmentpgm/misalignment.py
Misalignmentpgm-0.4.dist-info/METADATA
Misalignmentpgm-0.4.dist-info/WHEEL
Misalignmentpgm-0.4.dist-info/top_level.txt
Misalignmentpgm-0.4.dist-info/RECORD
