Metadata-Version: 2.1
Name: Misalignmentpgm
Version: 0.4
Summary: My first Python package
Author: Supriya
Author-email: <supriyasuhas058@email.com>
Keywords: python,first package
Requires-Dist: pandas
Requires-Dist: matplotlib
Requires-Dist: paho-mqtt
Requires-Dist: numpy
Requires-Dist: scipy
Requires-Dist: scikit-learn
Requires-Dist: logging
Requires-Dist: Werkzeug
Requires-Dist: flask
Requires-Dist: Flask-API
Requires-Dist: concurrent-log-handler
Requires-Dist: requests
Requires-Dist: waitress
Requires-Dist: nltk
